{
    "dependencies": [
        {
            "assetId": "1aPW5eMfMPeP1615dXiqyN",
            "exportId": "191b4dd1-3492-45a3-8711-326be9be4dda",
            "id": "0f7a0bbe-777c-41a5-b979-0b0430f25836",
            "name": "SpectaclesInteractionKit",
            "version": "0.15.0"
        },
        {
            "assetId": "7pJbKPpGSYDaQrYPtHhfiL",
            "exportId": "441558e9-2ed5-4f64-a93e-af802aa324ff",
            "id": "8c9a8f41-acd1-446a-b428-742bbc993c39",
            "name": "SpectaclesUIKit",
            "version": "0.0.8"
        }
    ]
}